Stemmer.pypy37-pp73-darwin.so
PyStemmer-3.0.0.dist-info/RECORD
PyStemmer-3.0.0.dist-info/LICENSE
PyStemmer-3.0.0.dist-info/AUTHORS
PyStemmer-3.0.0.dist-info/WHEEL
PyStemmer-3.0.0.dist-info/top_level.txt
PyStemmer-3.0.0.dist-info/METADATA
