Metadata-Version: 2.4
Name: PyStemmer
Version: 3.0.0
Summary: Snowball stemming algorithms, for information retrieval
Home-page: https://github.com/snowballstem/pystemmer/
Author: Richard Boulton
Author-email: richard@tartarus.org
Maintainer: Richard Boulton
Maintainer-email: richard@tartarus.org
License: MIT, BSD
Keywords: python,information retrieval,language processing,morphological analysis,stemming algorithms,stemmers
Platform: any
Classifier: Development Status :: 5 - Production/Stable
Classifier: Intended Audience :: Developers
Classifier: License :: OSI Approved :: MIT License
Classifier: License :: OSI Approved :: BSD License
Classifier: Natural Language :: Arabic
Classifier: Natural Language :: Basque
Classifier: Natural Language :: Catalan
Classifier: Natural Language :: Danish
Classifier: Natural Language :: Dutch
Classifier: Natural Language :: English
Classifier: Natural Language :: Esperanto
Classifier: Natural Language :: Finnish
Classifier: Natural Language :: French
Classifier: Natural Language :: German
Classifier: Natural Language :: Greek
Classifier: Natural Language :: Hindi
Classifier: Natural Language :: Hungarian
Classifier: Natural Language :: Indonesian
Classifier: Natural Language :: Irish
Classifier: Natural Language :: Italian
Classifier: Natural Language :: Lithuanian
Classifier: Natural Language :: Nepali
Classifier: Natural Language :: Norwegian
Classifier: Natural Language :: Portuguese
Classifier: Natural Language :: Romanian
Classifier: Natural Language :: Russian
Classifier: Natural Language :: Serbian
Classifier: Natural Language :: Spanish
Classifier: Natural Language :: Swedish
Classifier: Natural Language :: Tamil
Classifier: Natural Language :: Turkish
Classifier: Operating System :: OS Independent
Classifier: Programming Language :: C
Classifier: Programming Language :: Other
Classifier: Programming Language :: Python
Classifier: Programming Language :: Python :: 2
Classifier: Programming Language :: Python :: 2.6
Classifier: Programming Language :: Python :: 2.7
Classifier: Programming Language :: Python :: 3
Classifier: Programming Language :: Python :: 3.3
Classifier: Programming Language :: Python :: 3.4
Classifier: Programming Language :: Python :: 3.5
Classifier: Programming Language :: Python :: 3.6
Classifier: Programming Language :: Python :: 3.7
Classifier: Programming Language :: Python :: 3.8
Classifier: Programming Language :: Python :: 3.9
Classifier: Programming Language :: Python :: 3.10
Classifier: Programming Language :: Python :: 3.11
Classifier: Programming Language :: Python :: 3.12
Classifier: Programming Language :: Python :: 3.13
Classifier: Topic :: Database
Classifier: Topic :: Internet :: WWW/HTTP :: Indexing/Search
Classifier: Topic :: Text Processing :: Indexing
Classifier: Topic :: Text Processing :: Linguistic
License-File: LICENSE
License-File: AUTHORS
Dynamic: author
Dynamic: author-email
Dynamic: classifier
Dynamic: description
Dynamic: home-page
Dynamic: keywords
Dynamic: license
Dynamic: license-file
Dynamic: maintainer
Dynamic: maintainer-email
Dynamic: platform
Dynamic: summary
